jpl.edrn.dmcc.passwordrelay-0.0.3-py3.10-nspkg.pth
jpl/edrn/dmcc/passwordrelay/VERSION.txt
jpl/edrn/dmcc/passwordrelay/__init__.py
jpl/edrn/dmcc/passwordrelay/constants.py
jpl/edrn/dmcc/passwordrelay/main.py
jpl/edrn/dmcc/passwordrelay/server.py
jpl/edrn/dmcc/passwordrelay/utils.py
jpl.edrn.dmcc.passwordrelay-0.0.3.dist-info/LICENSE.md
jpl.edrn.dmcc.passwordrelay-0.0.3.dist-info/METADATA
jpl.edrn.dmcc.passwordrelay-0.0.3.dist-info/WHEEL
jpl.edrn.dmcc.passwordrelay-0.0.3.dist-info/entry_points.txt
jpl.edrn.dmcc.passwordrelay-0.0.3.dist-info/namespace_packages.txt
jpl.edrn.dmcc.passwordrelay-0.0.3.dist-info/top_level.txt
jpl.edrn.dmcc.passwordrelay-0.0.3.dist-info/zip-safe
jpl.edrn.dmcc.passwordrelay-0.0.3.dist-info/RECORD
