Metadata-Version: 2.1
Name: jpl.edrn.dmcc.passwordrelay
Version: 0.0.3
Summary: Relay server for EDRN DMCC password verification
Home-page: https://github.com/EDRN/jpl.edrn.dmcc.passwordrelay
Author: Sean Kelly
Author-email: kelly@seankelly.biz
License: apache-2.0
Keywords: ldap directory cancer password SOAP
Classifier: Development Status :: 4 - Beta
Classifier: Environment :: Console
Classifier: Intended Audience :: Developers
Classifier: Intended Audience :: Healthcare Industry
Classifier: License :: OSI Approved :: Apache Software License
Classifier: Operating System :: OS Independent
Classifier: Programming Language :: Python :: 3
Classifier: Topic :: Scientific/Engineering :: Bio-Informatics
Requires-Python: >=3.6
License-File: LICENSE.md
Requires-Dist: zeep (~=4.1.0)
